piano_sdk/__init__.py
piano_sdk/api_requestor.py
piano_sdk/enums.py
piano_sdk/error.py
piano_sdk/resources.py
piano_sdk/security_utils.py
hr_piano_sdk-0.8.1.dist-info/METADATA
hr_piano_sdk-0.8.1.dist-info/WHEEL
hr_piano_sdk-0.8.1.dist-info/top_level.txt
hr_piano_sdk-0.8.1.dist-info/RECORD
