Metadata-Version: 2.1
Name: hr-piano-sdk
Version: 0.8.1
Summary: A piano API implementation
Home-page: https://github.com/andrew-harper/piano_sdk
Author: Ramiro Rinaldi
Author-email: dev@hideawayreport.com
License: UNKNOWN
Platform: UNKNOWN
Classifier: Programming Language :: Python :: 2
Classifier: Operating System :: OS Independent
Requires-Dist: inflect
Requires-Dist: requests
Requires-Dist: pycrypto
Requires-Dist: backoff
